stucco_evolution/__init__.py
stucco_evolution/paster.py
stucco_evolution/test.py
stucco_evolution/+template+/evolve/__init__.py_tmpl
stucco_evolution/+template+/evolve/create.py
stucco_evolution/+template+/evolve/evolve1.py
stucco_evolution/evolve/__init__.py
stucco_evolution/evolve/create.py
stucco_evolution/evolve/evolve1.py
stucco_evolution/evolve/evolve2.py
stucco_evolution-0.50.0.dist-info/METADATA
stucco_evolution-0.50.0.dist-info/WHEEL
stucco_evolution-0.50.0.dist-info/entry_points.txt
stucco_evolution-0.50.0.dist-info/top_level.txt
stucco_evolution-0.50.0.dist-info/RECORD
