Metadata-Version: 2.1
Name: stucco-evolution
Version: 0.50.0
Summary: Moderately simple schema upgrades for SQLAlchemy.
Home-page: http://bitbucket.org/dholth/stucco_evolution
Author: Daniel Holth
Author-email: dholth@fastmail.fm
License: BSD
Keywords: sqlalchemy stucco
Platform: UNKNOWN
Classifier: Programming Language :: Python
Classifier: License :: OSI Approved :: BSD License
Classifier: Intended Audience :: Developers
Classifier: Topic :: Database :: Front-Ends
Obsoletes: ponzi_evolution
Requires-Dist: SQLAlchemy
Requires-Dist: repoze.evolution
Requires-Dist: six
